pretix_attendance_certificate/__init__.py
pretix_attendance_certificate/apps.py
pretix_attendance_certificate/locale/de/LC_MESSAGES/django.po
pretix_attendance_certificate/locale/de_Informal/.gitkeep
pretix_attendance_certificate/locale/de_Informal/LC_MESSAGES/django.po
pretix_attendance_certificate/migrations/0001_initial.py
pretix_attendance_certificate/migrations/__init__.py
pretix_attendance_certificate/models.py
pretix_attendance_certificate/render.py
pretix_attendance_certificate/signals.py
pretix_attendance_certificate/static/pretix_attendance_certificate/.gitkeep
pretix_attendance_certificate/static/pretix_attendance_certificate/empty_attendance_certificate.pdf
pretix_attendance_certificate/tasks.py
pretix_attendance_certificate/templates/pretix_attendance_certificate/.gitkeep
pretix_attendance_certificate/templates/pretix_attendance_certificate/history_fragment_attendance_certificate.html
pretix_attendance_certificate/templates/pretix_attendance_certificate/send_form_fragment_attendance_certificate.html
pretix_attendance_certificate/urls.py
pretix_attendance_certificate/views/__init__.py
pretix_attendance_certificate/views/editor.py
pretix_attendance_certificate/views/emails.py
pretix_plugin_attendance_certificate-0.1.11.dist-info/METADATA
pretix_plugin_attendance_certificate-0.1.11.dist-info/WHEEL
pretix_plugin_attendance_certificate-0.1.11.dist-info/entry_points.txt
pretix_plugin_attendance_certificate-0.1.11.dist-info/licenses/LICENSE
pretix_plugin_attendance_certificate-0.1.11.dist-info/RECORD
